pinax/__init__.py
pinax/points/__init__.py
pinax/points/admin.py
pinax/points/apps.py
pinax/points/forms.py
pinax/points/models.py
pinax/points/signals.py
pinax/points/migrations/0001_initial.py
pinax/points/migrations/__init__.py
pinax/points/templatetags/__init__.py
pinax/points/templatetags/pinax_points_tags.py
pinax/points/tests/__init__.py
pinax/points/tests/settings.py
pinax/points/tests/test_points.py
pinax/points/tests/urls.py
pinax_points-2.0.0.dist-info/AUTHORS
pinax_points-2.0.0.dist-info/LICENSE
pinax_points-2.0.0.dist-info/METADATA
pinax_points-2.0.0.dist-info/WHEEL
pinax_points-2.0.0.dist-info/top_level.txt
pinax_points-2.0.0.dist-info/RECORD
